README.md
setup.py
CronDecorator/__init__.py
Flask_CronDecorator.egg-info/PKG-INFO
Flask_CronDecorator.egg-info/SOURCES.txt
Flask_CronDecorator.egg-info/dependency_links.txt
Flask_CronDecorator.egg-info/requires.txt
Flask_CronDecorator.egg-info/top_level.txt